<?xml version="1.0" encoding="UTF-8"?>
<qes:espresso xsi:schemaLocation="http://www.quantum-espresso.org/ns/qes/qes-1.0 http://www.quantum-espresso.org/ns/qes/qes_190304.xsd" Units="Hartree atomic units" xmlns:xsi="http://www.w3.org/2001/XMLSchema-instance" xmlns:qes="http://www.quantum-espresso.org/ns/qes/qes-1.0">
  <!--If not explicitely indicated, all quantities are expressed in Hartree atomic units-->
  <general_info>
    <xml_format NAME="QEXSD" VERSION="19.03">QEXSD_19.03</xml_format>
    <creator NAME="PWSCF" VERSION="6.4.1">XML file generated by PWSCF</creator>
    <created DATE=" 4May2022" TIME="14: 2:33">This run was terminated on:  14: 2:33   4 May 2022</created>
    <job></job>
  </general_info>
  <parallel_info>
    <nprocs>120</nprocs>
    <nthreads>1</nthreads>
    <ntasks>1</ntasks>
    <nbgrp>1</nbgrp>
    <npool>1</npool>
    <ndiag>120</ndiag>
  </parallel_info>
  <input>
    <control_variables>
      <title></title>
      <calculation>relax</calculation>
      <restart_mode>from_scratch</restart_mode>
      <prefix>CCOrand5</prefix>
      <pseudo_dir>./</pseudo_dir>
      <outdir>./</outdir>
      <stress>true</stress>
      <forces>true</forces>
      <wf_collect>true</wf_collect>
      <disk_io>low</disk_io>
      <max_seconds>10000000</max_seconds>
      <nstep>50</nstep>
      <etot_conv_thr>5.000000000000000e-5</etot_conv_thr>
      <forc_conv_thr>5.000000000000000e-4</forc_conv_thr>
      <press_conv_thr>5.000000000000000e-1</press_conv_thr>
      <verbosity>low</verbosity>
      <print_every>100000</print_every>
    </control_variables>
    <atomic_species ntyp="3">
      <species name="Ca">
        <mass>4.007800000000000e1</mass>
        <pseudo_file>Ca_PBE.UPF</pseudo_file>
      </species>
      <species name="C">
        <mass>1.201070000000000e1</mass>
        <pseudo_file>C_PBE.UPF</pseudo_file>
      </species>
      <species name="O">
        <mass>1.600000000000000e1</mass>
        <pseudo_file>O_PBE.UPF</pseudo_file>
      </species>
    </atomic_species>
    <atomic_structure nat="10" alat="1.163030000000e1" bravais_index="5">
      <atomic_positions>
        <atom name="Ca" index="1">0.000000000000000e0 -3.815563032194547e-13 1.521725980905047e1</atom>
        <atom name="Ca" index="2">0.000000000000000e0 0.000000000000000e0 0.000000000000000e0</atom>
        <atom name="C" index="3">0.000000000000000e0 -1.907781516097273e-13 7.608629904525233e0</atom>
        <atom name="C" index="4">-1.614028355412245e-16 -5.726572605002644e-13 2.282588971357570e1</atom>
        <atom name="O" index="5">1.265911606953385e0 3.494740144015389e0 1.775346977722554e1</atom>
        <atom name="O" index="6">2.393577940866794e0 -2.843681682575400e0 1.775346977722554e1</atom>
        <atom name="O" index="7">-3.659489547820179e0 -6.510584614413256e-1 1.775346977722554e1</atom>
        <atom name="O" index="8">-2.393577940866794e0 2.843681682574636e0 1.268104984087539e1</atom>
        <atom name="O" index="9">3.659489547820178e0 6.510584614405626e-1 1.268104984087539e1</atom>
        <atom name="O" index="10">-1.265911606953385e0 -3.494740144016153e0 1.268104984087539e1</atom>
      </atomic_positions>
      <cell>
        <a1>4.925401154773564e0 -2.843681682575209e0 1.014483987270031e1</a1>
        <a2>0.000000000000000e0 5.687363365149655e0 1.014483987270031e1</a2>
        <a3>-4.925401154773564e0 -2.843681682575209e0 1.014483987270031e1</a3>
      </cell>
    </atomic_structure>
    <dft>
      <functional>PBE</functional>
    </dft>
    <spin>
      <lsda>false</lsda>
      <noncolin>false</noncolin>
      <spinorbit>false</spinorbit>
    </spin>
    <bands>
      <tot_charge>0.000000000000000e0</tot_charge>
      <occupations>fixed</occupations>
    </bands>
    <basis>
      <gamma_only>false</gamma_only>
      <ecutwfc>3.500000000000000e1</ecutwfc>
      <ecutrho>1.400000000000000e2</ecutrho>
    </basis>
    <electron_control>
      <diagonalization>cg</diagonalization>
      <mixing_mode>plain</mixing_mode>
      <mixing_beta>7.000000000000000e-1</mixing_beta>
      <conv_thr>4.999999999999999e-9</conv_thr>
      <mixing_ndim>8</mixing_ndim>
      <max_nstep>100</max_nstep>
      <real_space_q>false</real_space_q>
      <real_space_beta>false</real_space_beta>
      <tq_smoothing>false</tq_smoothing>
      <tbeta_smoothing>false</tbeta_smoothing>
      <diago_thr_init>0.000000000000000e0</diago_thr_init>
      <diago_full_acc>false</diago_full_acc>
      <diago_cg_maxiter>20</diago_cg_maxiter>
      <diago_ppcg_maxiter>20</diago_ppcg_maxiter>
    </electron_control>
    <k_points_IBZ>
      <monkhorst_pack nk1="5" nk2="5" nk3="5" k1="0" k2="0" k3="0">Monkhorst-Pack</monkhorst_pack>
    </k_points_IBZ>
    <ion_control>
      <ion_dynamics>bfgs</ion_dynamics>
      <upscale>1.000000000000000e2</upscale>
      <remove_rigid_rot>false</remove_rigid_rot>
      <refold_pos>false</refold_pos>
      <bfgs>
        <ndim>1</ndim>
        <trust_radius_min>1.000000000000000e-4</trust_radius_min>
        <trust_radius_max>8.000000000000000e-1</trust_radius_max>
        <trust_radius_init>5.000000000000000e-1</trust_radius_init>
        <w1>1.000000000000000e-2</w1>
        <w2>5.000000000000000e-1</w2>
      </bfgs>
    </ion_control>
    <cell_control>
      <cell_dynamics>none</cell_dynamics>
      <pressure>0.000000000000000e0</pressure>
      <wmass>1.824505386350088e5</wmass>
      <cell_factor>0.000000000000000e0</cell_factor>
      <fix_volume>false</fix_volume>
      <fix_area>false</fix_area>
      <isotropic>false</isotropic>
    </cell_control>
    <symmetry_flags>
      <nosym>false</nosym>
      <nosym_evc>false</nosym_evc>
      <noinv>false</noinv>
      <no_t_rev>false</no_t_rev>
      <force_symmorphic>false</force_symmorphic>
      <use_all_frac>false</use_all_frac>
    </symmetry_flags>
    <free_positions rank="2" dims="3 10" order="F">
      1 1 1
      1 1 1
      1 1 1
      1 1 1
      1 1 1
      1 1 1
      1 1 1
      1 1 1
      1 1 1
      1 1 1
      </free_positions>
  </input>
  <step n_step="1">
    <scf_conv>
      <convergence_achieved>true</convergence_achieved>
      <n_scf_steps>10</n_scf_steps>
      <scf_error>8.604577087766062e-10</scf_error>
    </scf_conv>
    <atomic_structure nat="10" alat="1.163030000000e1" bravais_index="5">
      <atomic_positions>
        <atom name="Ca" index="1">-4.939098270520172e-17 -3.812370443399785e-13 1.521725980905047e1</atom>
        <atom name="Ca" index="2">0.000000000000000e0 0.000000000000000e0 0.000000000000000e0</atom>
        <atom name="C" index="3">-2.469549135260086e-17 -1.906185221699893e-13 7.608629904525233e0</atom>
        <atom name="C" index="4">-1.614028355412245e-16 -5.726572605002644e-13 2.282588971357570e1</atom>
        <atom name="O" index="5">1.220570447215335e0 3.573273336355800e0 1.775346977722554e1</atom>
        <atom name="O" index="6">2.484260260342892e0 -2.843681682575399e0 1.775346977722554e1</atom>
        <atom name="O" index="7">-3.704830707558228e0 -7.295916537817360e-1 1.775346977722554e1</atom>
        <atom name="O" index="8">-2.484260260342892e0 2.843681682574636e0 1.268104984087539e1</atom>
        <atom name="O" index="9">3.704830707558227e0 7.295916537809735e-1 1.268104984087539e1</atom>
        <atom name="O" index="10">-1.220570447215336e0 -3.573273336356563e0 1.268104984087539e1</atom>
      </atomic_positions>
      <cell>
        <a1>4.925401154773564e0 -2.843681682575209e0 1.014483987270031e1</a1>
        <a2>0.000000000000000e0 5.687363365149655e0 1.014483987270031e1</a2>
        <a3>-4.925401154773564e0 -2.843681682575209e0 1.014483987270031e1</a3>
      </cell>
    </atomic_structure>
    <total_energy>
      <etot>-1.837008366192446e2</etot>
      <eband>-1.640886437526057e1</eband>
      <ehart>4.963250995483367e1</ehart>
      <vtxc>-4.595234052520364e1</vtxc>
      <etxc>-3.746869067109965e1</etxc>
      <ewald>-1.261429227983462e2</ewald>
    </total_energy>
    <forces rank="2" dims="3 10" order="F">
      0.000000000000000e0 0.000000000000000e0 0.000000000000000e0
      0.000000000000000e0 0.000000000000000e0 0.000000000000000e0
      -1.383214237883558e-45 -3.335406458547580e-29 -3.739766962961251e-29
      5.777093450096858e-29 3.335406458547581e-29 -1.869883481480500e-29
      -2.636656450507175e-1 4.566822934383374e-1 1.145828168667301e-14
      5.273312901014351e-1 -1.274159715669727e-18 7.460130792115355e-18
      -2.636656450507175e-1 -4.566822934383374e-1 -1.145336384813366e-14
      -5.273312901014351e-1 1.274159715669727e-18 -7.460130792115355e-18
      2.636656450507175e-1 4.566822934383374e-1 1.145336384813366e-14
      2.636656450507175e-1 -4.566822934383374e-1 -1.145828168667301e-14
      </forces>
  </step>
  <step n_step="2">
    <scf_conv>
      <convergence_achieved>true</convergence_achieved>
      <n_scf_steps>8</n_scf_steps>
      <scf_error>2.581804626804137e-9</scf_error>
    </scf_conv>
    <atomic_structure nat="10" alat="1.163030000000e1" bravais_index="5">
      <atomic_positions>
        <atom name="Ca" index="1">-4.939098270520172e-17 -3.812370443399785e-13 1.521725980905047e1</atom>
        <atom name="Ca" index="2">0.000000000000000e0 0.000000000000000e0 0.000000000000000e0</atom>
        <atom name="C" index="3">-2.469549135260086e-17 -1.906185221699893e-13 7.608629904525233e0</atom>
        <atom name="C" index="4">-1.614028355412245e-16 -5.726572605002644e-13 2.282588971357570e1</atom>
        <atom name="O" index="5">1.228426989381456e0 3.559665406152269e0 1.775346977722554e1</atom>
        <atom name="O" index="6">2.468547176010649e0 -2.843681682575399e0 1.775346977722554e1</atom>
        <atom name="O" index="7">-3.696974165392107e0 -7.159837235782041e-1 1.775346977722554e1</atom>
        <atom name="O" index="8">-2.468547176010651e0 2.843681682574636e0 1.268104984087539e1</atom>
        <atom name="O" index="9">3.696974165392106e0 7.159837235774419e-1 1.268104984087539e1</atom>
        <atom name="O" index="10">-1.228426989381456e0 -3.559665406153032e0 1.268104984087539e1</atom>
      </atomic_positions>
      <cell>
        <a1>4.925401154773564e0 -2.843681682575209e0 1.014483987270031e1</a1>
        <a2>0.000000000000000e0 5.687363365149655e0 1.014483987270031e1</a2>
        <a3>-4.925401154773564e0 -2.843681682575209e0 1.014483987270031e1</a3>
      </cell>
    </atomic_structure>
    <total_energy>
      <etot>-1.837113690483668e2</etot>
      <eband>-1.668022267462715e1</eband>
      <ehart>5.122700431016663e1</ehart>
      <vtxc>-4.616787948458762e1</vtxc>
      <etxc>-3.763420857708621e1</etxc>
      <ewald>-1.243377678805708e2</ewald>
    </total_energy>
    <forces rank="2" dims="3 10" order="F">
      -2.166410043786322e-29 -1.250777421955343e-29 7.012063055551878e-30
      0.000000000000000e0 0.000000000000000e0 0.000000000000000e0
      -2.888546725048429e-29 5.003109687821372e-29 8.414475666662756e-29
      8.665640175145287e-29 -1.667703229273790e-29 9.349417407402507e-30
      5.526267552612972e-2 -9.571776177346520e-2 -2.403082070392164e-15
      -1.105253510522595e-1 -3.912123787174785e-18 8.781414098408366e-19
      5.526267552612972e-2 9.571776177346520e-2 2.402630790267669e-15
      1.105253510522595e-1 3.912123787174785e-18 -8.781414098408366e-19
      -5.526267552612972e-2 -9.571776177346520e-2 -2.402630790267669e-15
      -5.526267552612972e-2 9.571776177346520e-2 2.403082070392166e-15
      </forces>
  </step>
  <step n_step="3">
    <scf_conv>
      <convergence_achieved>true</convergence_achieved>
      <n_scf_steps>8</n_scf_steps>
      <scf_error>4.055808306324808e-10</scf_error>
    </scf_conv>
    <atomic_structure nat="10" alat="1.163030000000e1" bravais_index="5">
      <atomic_positions>
        <atom name="Ca" index="1">-4.939098270520172e-17 -3.812370443399785e-13 1.521725980905047e1</atom>
        <atom name="Ca" index="2">2.188026364119843e-46 2.531762577052654e-30 -1.419347560993433e-30</atom>
        <atom name="C" index="3">-2.469549135260086e-17 -1.906185221699893e-13 7.608629904525233e0</atom>
        <atom name="C" index="4">-1.614028355412245e-16 -5.726572605002644e-13 2.282588971357570e1</atom>
        <atom name="O" index="5">1.227506247413791e0 3.561260178020926e0 1.775346977722554e1</atom>
        <atom name="O" index="6">2.470388659945982e0 -2.843681682575399e0 1.775346977722554e1</atom>
        <atom name="O" index="7">-3.697894907359772e0 -7.175784954468618e-1 1.775346977722553e1</atom>
        <atom name="O" index="8">-2.470388659945982e0 2.843681682574636e0 1.268104984087539e1</atom>
        <atom name="O" index="9">3.697894907359771e0 7.175784954461010e-1 1.268104984087539e1</atom>
        <atom name="O" index="10">-1.227506247413791e0 -3.561260178021690e0 1.268104984087539e1</atom>
      </atomic_positions>
      <cell>
        <a1>4.925401154773564e0 -2.843681682575209e0 1.014483987270031e1</a1>
        <a2>0.000000000000000e0 5.687363365149655e0 1.014483987270031e1</a2>
        <a3>-4.925401154773564e0 -2.843681682575209e0 1.014483987270031e1</a3>
      </cell>
    </atomic_structure>
    <total_energy>
      <etot>-1.837117533948141e2</etot>
      <eband>-1.663193416437835e1</eband>
      <ehart>5.093018037691802e1</ehart>
      <vtxc>-4.612863851484836e1</vtxc>
      <etxc>-3.760405717227592e1</etxc>
      <ewald>-1.246742716357888e2</ewald>
    </total_energy>
    <forces rank="2" dims="3 10" order="F">
      -1.444273362524215e-29 2.501554843910686e-29 6.273093301819483e-43
      9.628288363754651e-46 1.667703229273790e-29 -9.349417407402507e-30
      5.777093450096858e-29 -1.000621937564274e-28 -5.609650444442005e-29
      -5.777093450096858e-29 3.335406458547581e-29 -1.869883481480500e-29
      -7.336235639216850e-3 1.270673286342316e-2 3.190952931629298e-16
      1.467247127843370e-2 8.246895362276979e-20 1.053426443298131e-19
      -7.336235639216849e-3 -1.270673286342316e-2 -3.192944622240623e-16
      -1.467247127843370e-2 -8.246895362276979e-20 -1.053426443298131e-19
      7.336235639216849e-3 1.270673286342316e-2 3.192944622240623e-16
      7.336235639216850e-3 -1.270673286342316e-2 -3.190952931629275e-16
      </forces>
  </step>
  <step n_step="4">
    <scf_conv>
      <convergence_achieved>true</convergence_achieved>
      <n_scf_steps>7</n_scf_steps>
      <scf_error>6.934982734932658e-11</scf_error>
    </scf_conv>
    <atomic_structure nat="10" alat="1.163030000000e1" bravais_index="5">
      <atomic_positions>
        <atom name="Ca" index="1">-4.939098270520172e-17 -3.812370443399785e-13 1.521725980905047e1</atom>
        <atom name="Ca" index="2">2.382839440752747e-46 2.531762577052654e-30 -1.419347560993433e-30</atom>
        <atom name="C" index="3">-2.469549135260086e-17 -1.906185221699893e-13 7.608629904525233e0</atom>
        <atom name="C" index="4">-1.614028355412245e-16 -5.726572605002644e-13 2.282588971357570e1</atom>
        <atom name="O" index="5">1.227506247413791e0 3.561260178020926e0 1.775346977722554e1</atom>
        <atom name="O" index="6">2.470388659945982e0 -2.843681682575399e0 1.775346977722554e1</atom>
        <atom name="O" index="7">-3.697894907359772e0 -7.175784954468618e-1 1.775346977722553e1</atom>
        <atom name="O" index="8">-2.470388659945982e0 2.843681682574636e0 1.268104984087539e1</atom>
        <atom name="O" index="9">3.697894907359771e0 7.175784954461013e-1 1.268104984087539e1</atom>
        <atom name="O" index="10">-1.227506247413791e0 -3.561260178021689e0 1.268104984087539e1</atom>
      </atomic_positions>
      <cell>
        <a1>4.925401154773564e0 -2.843681682575209e0 1.014483987270031e1</a1>
        <a2>0.000000000000000e0 5.687363365149655e0 1.014483987270031e1</a2>
        <a3>-4.925401154773564e0 -2.843681682575209e0 1.014483987270031e1</a3>
      </cell>
    </atomic_structure>
    <total_energy>
      <etot>-1.837117605925820e2</etot>
      <eband>-1.663752597456143e1</eband>
      <ehart>5.096445400793563e1</ehart>
      <vtxc>-4.613317957649753e1</vtxc>
      <etxc>-3.760754569648054e1</etxc>
      <ewald>-1.246353655411683e2</ewald>
    </total_energy>
    <forces rank="2" dims="3 10" order="F">
      0.000000000000000e0 0.000000000000000e0 0.000000000000000e0
      -1.925657672750930e-45 -3.335406458547581e-29 1.869883481480501e-29
      -5.777093450096858e-29 3.335406458547581e-29 -1.869883481480500e-29
      5.777093450096858e-29 1.000621937564274e-28 2.508594560671241e-42
      -1.920780747654734e-4 3.326889845138667e-4 8.360752655749700e-18
      3.841561495309469e-4 1.362701936979378e-20 7.227298559769075e-21
      -1.920780747654734e-4 -3.326889845138667e-4 -8.352389471907745e-18
      -3.841561495309469e-4 -1.362701936979378e-20 -7.227298559769075e-21
      1.920780747654734e-4 3.326889845138667e-4 8.352389471907745e-18
      1.920780747654735e-4 -3.326889845138667e-4 -8.333558407126256e-18
      </forces>
  </step>
  <output>
    <convergence_info>
      <scf_conv>
        <convergence_achieved>true</convergence_achieved>
        <n_scf_steps>7</n_scf_steps>
        <scf_error>6.934982734932658e-11</scf_error>
      </scf_conv>
      <opt_conv>
        <convergence_achieved>true</convergence_achieved>
        <n_opt_steps>3</n_opt_steps>
        <grad_norm>1.618163844274371e-4</grad_norm>
      </opt_conv>
    </convergence_info>
    <algorithmic_info>
      <real_space_q>false</real_space_q>
      <real_space_beta>false</real_space_beta>
      <uspp>true</uspp>
      <paw>false</paw>
    </algorithmic_info>
    <atomic_species ntyp="3" pseudo_dir="./">
      <species name="Ca">
        <mass>4.007800000000000e1</mass>
        <pseudo_file>Ca_PBE.UPF</pseudo_file>
      </species>
      <species name="C">
        <mass>1.201070000000000e1</mass>
        <pseudo_file>C_PBE.UPF</pseudo_file>
      </species>
      <species name="O">
        <mass>1.600000000000000e1</mass>
        <pseudo_file>O_PBE.UPF</pseudo_file>
      </species>
    </atomic_species>
    <atomic_structure nat="10" alat="1.163030000000e1" bravais_index="5">
      <atomic_positions>
        <atom name="Ca" index="1">-4.939098270520172e-17 -3.812370443399785e-13 1.521725980905047e1</atom>
        <atom name="Ca" index="2">2.382839440752747e-46 2.531762577052654e-30 -1.419347560993433e-30</atom>
        <atom name="C" index="3">-2.469549135260086e-17 -1.906185221699893e-13 7.608629904525233e0</atom>
        <atom name="C" index="4">-1.614028355412245e-16 -5.726572605002644e-13 2.282588971357570e1</atom>
        <atom name="O" index="5">1.227506247413791e0 3.561260178020926e0 1.775346977722554e1</atom>
        <atom name="O" index="6">2.470388659945982e0 -2.843681682575399e0 1.775346977722554e1</atom>
        <atom name="O" index="7">-3.697894907359772e0 -7.175784954468618e-1 1.775346977722553e1</atom>
        <atom name="O" index="8">-2.470388659945982e0 2.843681682574636e0 1.268104984087539e1</atom>
        <atom name="O" index="9">3.697894907359771e0 7.175784954461013e-1 1.268104984087539e1</atom>
        <atom name="O" index="10">-1.227506247413791e0 -3.561260178021689e0 1.268104984087539e1</atom>
      </atomic_positions>
      <cell>
        <a1>4.925401154773564e0 -2.843681682575209e0 1.014483987270031e1</a1>
        <a2>0.000000000000000e0 5.687363365149655e0 1.014483987270031e1</a2>
        <a3>-4.925401154773564e0 -2.843681682575209e0 1.014483987270031e1</a3>
      </cell>
    </atomic_structure>
    <symmetries>
      <nsym>12</nsym>
      <nrot>12</nrot>
      <space_group>0</space_group>
      <symmetry>
        <info name="identity">crystal_symmetry</info>
        <rotation rank="2" dims="3 3" order="F">
          1.000000000000000e0 0.000000000000000e0 0.000000000000000e0
          0.000000000000000e0 1.000000000000000e0 0.000000000000000e0
          0.000000000000000e0 0.000000000000000e0 1.000000000000000e0
          </rotation>
        <fractional_translation>0.000000000000000e0 0.000000000000000e0 0.000000000000000e0</fractional_translation>
        <equivalent_atoms nat="10" size="10">
          1 2 3 4 5 6 7 8
          9 10
          </equivalent_atoms>
      </symmetry>
      <symmetry>
        <info name="180 deg rotation - cart. axis [1,0,0]">crystal_symmetry</info>
        <rotation rank="2" dims="3 3" order="F">
          0.000000000000000e0 0.000000000000000e0 -1.000000000000000e0
          0.000000000000000e0 -1.000000000000000e0 0.000000000000000e0
          -1.000000000000000e0 0.000000000000000e0 0.000000000000000e0
          </rotation>
        <fractional_translation>-4.999999999999999e-1 5.000000000000000e-1 -4.999999999999999e-1</fractional_translation>
        <equivalent_atoms nat="10" size="10">
          2 1 3 4 7 6 5 8
          10 9
          </equivalent_atoms>
      </symmetry>
      <symmetry>
        <info name="120 deg rotation - cryst. axis [0,0,1]">crystal_symmetry</info>
        <rotation rank="2" dims="3 3" order="F">
          0.000000000000000e0 0.000000000000000e0 1.000000000000000e0
          1.000000000000000e0 0.000000000000000e0 0.000000000000000e0
          0.000000000000000e0 1.000000000000000e0 0.000000000000000e0
          </rotation>
        <fractional_translation>0.000000000000000e0 0.000000000000000e0 0.000000000000000e0</fractional_translation>
        <equivalent_atoms nat="10" size="10">
          1 2 3 4 7 5 6 10
          8 9
          </equivalent_atoms>
      </symmetry>
      <symmetry>
        <info name="120 deg rotation - cryst. axis [0,0,-1]">crystal_symmetry</info>
        <rotation rank="2" dims="3 3" order="F">
          0.000000000000000e0 1.000000000000000e0 0.000000000000000e0
          0.000000000000000e0 0.000000000000000e0 1.000000000000000e0
          1.000000000000000e0 0.000000000000000e0 0.000000000000000e0
          </rotation>
        <fractional_translation>0.000000000000000e0 0.000000000000000e0 0.000000000000000e0</fractional_translation>
        <equivalent_atoms nat="10" size="10">
          1 2 3 4 6 7 5 9
          10 8
          </equivalent_atoms>
      </symmetry>
      <symmetry>
        <info name="180 deg rotation - cryst. axis [0,1,0]">crystal_symmetry</info>
        <rotation rank="2" dims="3 3" order="F">
          0.000000000000000e0 -1.000000000000000e0 0.000000000000000e0
          -1.000000000000000e0 0.000000000000000e0 0.000000000000000e0
          0.000000000000000e0 0.000000000000000e0 -1.000000000000000e0
          </rotation>
        <fractional_translation>-4.999999999999999e-1 5.000000000000000e-1 -4.999999999999999e-1</fractional_translation>
        <equivalent_atoms nat="10" size="10">
          2 1 3 4 5 7 6 9
          8 10
          </equivalent_atoms>
      </symmetry>
      <symmetry>
        <info name="180 deg rotation - cryst. axis [1,1,0]">crystal_symmetry</info>
        <rotation rank="2" dims="3 3" order="F">
          -1.000000000000000e0 0.000000000000000e0 0.000000000000000e0
          0.000000000000000e0 0.000000000000000e0 -1.000000000000000e0
          0.000000000000000e0 -1.000000000000000e0 0.000000000000000e0
          </rotation>
        <fractional_translation>-4.999999999999999e-1 5.000000000000000e-1 -4.999999999999999e-1</fractional_translation>
        <equivalent_atoms nat="10" size="10">
          2 1 3 4 6 5 7 10
          9 8
          </equivalent_atoms>
      </symmetry>
      <symmetry>
        <info name="inversion">crystal_symmetry</info>
        <rotation rank="2" dims="3 3" order="F">
          -1.000000000000000e0 0.000000000000000e0 0.000000000000000e0
          0.000000000000000e0 -1.000000000000000e0 0.000000000000000e0
          0.000000000000000e0 0.000000000000000e0 -1.000000000000000e0
          </rotation>
        <fractional_translation>0.000000000000000e0 0.000000000000000e0 0.000000000000000e0</fractional_translation>
        <equivalent_atoms nat="10" size="10">
          1 2 4 3 10 8 9 6
          7 5
          </equivalent_atoms>
      </symmetry>
      <symmetry>
        <info name="inv. 180 deg rotation - cart. axis [1,0,0]">crystal_symmetry</info>
        <rotation rank="2" dims="3 3" order="F">
          0.000000000000000e0 0.000000000000000e0 1.000000000000000e0
          0.000000000000000e0 1.000000000000000e0 0.000000000000000e0
          1.000000000000000e0 0.000000000000000e0 0.000000000000000e0
          </rotation>
        <fractional_translation>-4.999999999999999e-1 5.000000000000000e-1 -4.999999999999999e-1</fractional_translation>
        <equivalent_atoms nat="10" size="10">
          2 1 4 3 9 8 10 6
          5 7
          </equivalent_atoms>
      </symmetry>
      <symmetry>
        <info name="inv. 120 deg rotation - cryst. axis [0,0,1]">crystal_symmetry</info>
        <rotation rank="2" dims="3 3" order="F">
          0.000000000000000e0 0.000000000000000e0 -1.000000000000000e0
          -1.000000000000000e0 0.000000000000000e0 0.000000000000000e0
          0.000000000000000e0 -1.000000000000000e0 0.000000000000000e0
          </rotation>
        <fractional_translation>0.000000000000000e0 0.000000000000000e0 0.000000000000000e0</fractional_translation>
        <equivalent_atoms nat="10" size="10">
          1 2 4 3 9 10 8 5
          6 7
          </equivalent_atoms>
      </symmetry>
      <symmetry>
        <info name="inv. 120 deg rotation - cryst. axis [0,0,-1]">crystal_symmetry</info>
        <rotation rank="2" dims="3 3" order="F">
          0.000000000000000e0 -1.000000000000000e0 0.000000000000000e0
          0.000000000000000e0 0.000000000000000e0 -1.000000000000000e0
          -1.000000000000000e0 0.000000000000000e0 0.000000000000000e0
          </rotation>
        <fractional_translation>0.000000000000000e0 0.000000000000000e0 0.000000000000000e0</fractional_translation>
        <equivalent_atoms nat="10" size="10">
          1 2 4 3 8 9 10 7
          5 6
          </equivalent_atoms>
      </symmetry>
      <symmetry>
        <info name="inv. 180 deg rotation - cryst. axis [0,1,0]">crystal_symmetry</info>
        <rotation rank="2" dims="3 3" order="F">
          0.000000000000000e0 1.000000000000000e0 0.000000000000000e0
          1.000000000000000e0 0.000000000000000e0 0.000000000000000e0
          0.000000000000000e0 0.000000000000000e0 1.000000000000000e0
          </rotation>
        <fractional_translation>-4.999999999999999e-1 5.000000000000000e-1 -4.999999999999999e-1</fractional_translation>
        <equivalent_atoms nat="10" size="10">
          2 1 4 3 10 9 8 7
          6 5
          </equivalent_atoms>
      </symmetry>
      <symmetry>
        <info name="inv. 180 deg rotation - cryst. axis [1,1,0]">crystal_symmetry</info>
        <rotation rank="2" dims="3 3" order="F">
          1.000000000000000e0 0.000000000000000e0 0.000000000000000e0
          0.000000000000000e0 0.000000000000000e0 1.000000000000000e0
          0.000000000000000e0 1.000000000000000e0 0.000000000000000e0
          </rotation>
        <fractional_translation>-4.999999999999999e-1 5.000000000000000e-1 -4.999999999999999e-1</fractional_translation>
        <equivalent_atoms nat="10" size="10">
          2 1 4 3 8 10 9 5
          7 6
          </equivalent_atoms>
      </symmetry>
    </symmetries>
    <basis_set>
      <gamma_only>false</gamma_only>
      <ecutwfc>3.500000000000000e1</ecutwfc>
      <ecutrho>1.400000000000000e2</ecutrho>
      <fft_grid nr1="64" nr2="64" nr3="64"></fft_grid>
      <fft_smooth nr1="64" nr2="64" nr3="64"></fft_smooth>
      <fft_box nr1="64" nr2="64" nr3="64"></fft_box>
      <ngm>67453</ngm>
      <ngms>67453</ngms>
      <npwx>8493</npwx>
      <reciprocal_lattice>
        <b1>1.180644949978159e0 -6.816456796873716e-1 3.821417307037880e-1</b1>
        <b2>-7.578447637889197e-18 1.363291359374743e0 3.821417307038393e-1</b2>
        <b3>-1.180644949978159e0 -6.816456796873716e-1 3.821417307037880e-1</b3>
      </reciprocal_lattice>
    </basis_set>
    <dft>
      <functional>PBE</functional>
    </dft>
    <magnetization>
      <lsda>false</lsda>
      <noncolin>false</noncolin>
      <spinorbit>false</spinorbit>
      <total>0.000000000000000e0</total>
      <absolute>0.000000000000000e0</absolute>
      <do_magnetization>false</do_magnetization>
    </magnetization>
    <total_energy>
      <etot>-1.837117605925820e2</etot>
      <eband>-1.663752597456143e1</eband>
      <ehart>5.096445400793563e1</ehart>
      <vtxc>-4.613317957649753e1</vtxc>
      <etxc>-3.760754569648054e1</etxc>
      <ewald>-1.246353655411683e2</ewald>
    </total_energy>
    <band_structure>
      <lsda>false</lsda>
      <noncolin>false</noncolin>
      <spinorbit>false</spinorbit>
      <nbnd>32</nbnd>
      <nelec>6.400000000000000e1</nelec>
      <num_of_atomic_wfc>52</num_of_atomic_wfc>
      <wf_collected>true</wf_collected>
      <highestOccupiedLevel>1.644144780488927e-1</highestOccupiedLevel>
      <starting_k_points>
        <monkhorst_pack nk1="5" nk2="5" nk3="5" k1="0" k2="0" k3="0">Monkhorst-Pack</monkhorst_pack>
      </starting_k_points>
      <nks>19</nks>
      <occupations_kind>fixed</occupations_kind>
      <ks_energies>
        <k_point weight="1.600000000000e-2">0.000000000000000e0 0.000000000000000e0 0.000000000000000e0</k_point>
        <npw>8493</npw>
        <eigenvalues size="32">
          -1.241285162274040e0 -1.240785408349223e0 -6.225424122171583e-1 -6.199646312783824e-1 -5.562858014357507e-1
          -5.562858014357376e-1 -5.444126507416280e-1 -5.444126507416280e-1 -5.427982155549046e-1 -5.399789489031045e-1
          -5.072738515595931e-1 -5.072738515595194e-1 -4.883228960516665e-1 -4.883228960516026e-1 -1.179832611154629e-1
          -1.084896289110043e-1 -5.748511423179555e-2 -5.216316549022888e-2 -5.216316549022755e-2 -4.444953674786379e-2
          -4.444953674786202e-2 -6.140540691658757e-3 9.154996681434325e-2 9.154996681437167e-2 9.907369883603163e-2
          9.907369883605368e-2 1.092064633149195e-1 1.092064633149449e-1 1.389372181404042e-1 1.389372181404467e-1
          1.444613678974209e-1 1.608252424211576e-1
          </eigenvalues>
        <occupations size="32">
          1.000000000000000e0 1.000000000000000e0 1.000000000000000e0 1.000000000000000e0 1.000000000000000e0
          1.000000000000000e0 1.000000000000000e0 1.000000000000000e0 1.000000000000000e0 1.000000000000000e0
          1.000000000000000e0 1.000000000000000e0 1.000000000000000e0 1.000000000000000e0 1.000000000000000e0
          1.000000000000000e0 1.000000000000000e0 1.000000000000000e0 1.000000000000000e0 1.000000000000000e0
          1.000000000000000e0 1.000000000000000e0 1.000000000000000e0 1.000000000000000e0 1.000000000000000e0
          1.000000000000000e0 1.000000000000000e0 1.000000000000000e0 1.000000000000000e0 1.000000000000000e0
          1.000000000000000e0 1.000000000000000e0
          </occupations>
      </ks_energies>
      <ks_energies>
        <k_point weight="9.600000000000e-2">-2.361289899956318e-1 -1.363291359374743e-1 7.642834614075761e-2</k_point>
        <npw>8442</npw>
        <eigenvalues size="32">
          -1.241233349150753e0 -1.240829414644355e0 -6.233987746798155e-1 -6.191862904510506e-1 -5.561452405146998e-1
          -5.529995727375901e-1 -5.487210429252368e-1 -5.447962180752411e-1 -5.426356458678089e-1 -5.421812778976469e-1
          -5.049509773605358e-1 -5.006190103851846e-1 -4.931165992228205e-1 -4.895443814263232e-1 -1.133968904972745e-1
          -1.095418047728942e-1 -5.449042095384024e-2 -5.062140322806901e-2 -4.808944815232358e-2 -4.494353173032701e-2
          -4.443037604239169e-2 -1.177816281778359e-2 9.212015784919870e-2 9.388962385976656e-2 9.755452351981940e-2
          9.892563428576517e-2 1.033642215104638e-1 1.051302839601679e-1 1.324526156404378e-1 1.332227703398664e-1
          1.528311883467946e-1 1.593825180281437e-1
          </eigenvalues>
        <occupations size="32">
          1.000000000000000e0 1.000000000000000e0 1.000000000000000e0 1.000000000000000e0 1.000000000000000e0
          1.000000000000000e0 1.000000000000000e0 1.000000000000000e0 1.000000000000000e0 1.000000000000000e0
          1.000000000000000e0 1.000000000000000e0 1.000000000000000e0 1.000000000000000e0 1.000000000000000e0
          1.000000000000000e0 1.000000000000000e0 1.000000000000000e0 1.000000000000000e0 1.000000000000000e0
          1.000000000000000e0 1.000000000000000e0 1.000000000000000e0 1.000000000000000e0 1.000000000000000e0
          1.000000000000000e0 1.000000000000000e0 1.000000000000000e0 1.000000000000000e0 1.000000000000000e0
          1.000000000000000e0 1.000000000000000e0
          </occupations>
      </ks_energies>
      <ks_energies>
        <k_point weight="9.600000000000e-2">-4.722579799912635e-1 -2.726582718749486e-1 1.528566922815152e-1</k_point>
        <npw>8447</npw>
        <eigenvalues size="32">
          -1.241102114561548e0 -1.240948057281975e0 -6.228981542541179e-1 -6.199863034416180e-1 -5.544126673627012e-1
          -5.524280358527064e-1 -5.518289495878581e-1 -5.486764268790067e-1 -5.414837641742880e-1 -5.400016922755196e-1
          -5.003855366058922e-1 -4.970842755397030e-1 -4.963337638653870e-1 -4.934345525520211e-1 -1.084582147332263e-1
          -1.076051077330131e-1 -5.447247314724932e-2 -5.058580026399774e-2 -4.466752715573425e-2 -4.353581850104993e-2
          -3.393346876955341e-2 -2.117514864946343e-2 8.357978580693720e-2 8.663862335700770e-2 9.355911726362026e-2
          9.502333748302345e-2 1.079651104228784e-1 1.106454114716407e-1 1.238259829220953e-1 1.242504110034986e-1
          1.588845682791251e-1 1.602101577245604e-1
          </eigenvalues>
        <occupations size="32">
          1.000000000000000e0 1.000000000000000e0 1.000000000000000e0 1.000000000000000e0 1.000000000000000e0
          1.000000000000000e0 1.000000000000000e0 1.000000000000000e0 1.000000000000000e0 1.000000000000000e0
          1.000000000000000e0 1.000000000000000e0 1.000000000000000e0 1.000000000000000e0 1.000000000000000e0
          1.000000000000000e0 1.000000000000000e0 1.000000000000000e0 1.000000000000000e0 1.000000000000000e0
          1.000000000000000e0 1.000000000000000e0 1.000000000000000e0 1.000000000000000e0 1.000000000000000e0
          1.000000000000000e0 1.000000000000000e0 1.000000000000000e0 1.000000000000000e0 1.000000000000000e0
          1.000000000000000e0 1.000000000000000e0
          </occupations>
      </ks_energies>
      <ks_energies>
        <k_point weight="9.600000000000e-2">-2.361289899956318e-1 1.363291359374743e-1 1.528566922815255e-1</k_point>
        <npw>8430</npw>
        <eigenvalues size="32">
          -1.241223368640580e0 -1.240839188757912e0 -6.236288099640230e-1 -6.190098216093958e-1 -5.549975358174992e-1
          -5.544950692556649e-1 -5.460932231687126e-1 -5.453502846186174e-1 -5.437892300911442e-1 -5.431399406662076e-1
          -5.026401507016804e-1 -5.019367124721182e-1 -4.921063796012577e-1 -4.911011639522188e-1 -1.128811963832308e-1
          -1.105523476807532e-1 -5.230586804739275e-2 -5.085343182357242e-2 -4.999846162189803e-2 -4.422947864352995e-2
          -4.324507783840583e-2 -1.295771850981831e-2 9.188233114101154e-2 9.314303577978567e-2 9.659161033819828e-2
          9.912393872869089e-2 1.034778215721778e-1 1.083350557924653e-1 1.281784730197145e-1 1.356754204995883e-1
          1.530540306704997e-1 1.584166526479377e-1
          </eigenvalues>
        <occupations size="32">
          1.000000000000000e0 1.000000000000000e0 1.000000000000000e0 1.000000000000000e0 1.000000000000000e0
          1.000000000000000e0 1.000000000000000e0 1.000000000000000e0 1.000000000000000e0 1.000000000000000e0
          1.000000000000000e0 1.000000000000000e0 1.000000000000000e0 1.000000000000000e0 1.000000000000000e0
          1.000000000000000e0 1.000000000000000e0 1.000000000000000e0 1.000000000000000e0 1.000000000000000e0
          1.000000000000000e0 1.000000000000000e0 1.000000000000000e0 1.000000000000000e0 1.000000000000000e0
          1.000000000000000e0 1.000000000000000e0 1.000000000000000e0 1.000000000000000e0 1.000000000000000e0
          1.000000000000000e0 1.000000000000000e0
          </occupations>
      </ks_energies>
      <ks_energies>
        <k_point weight="1.920000000000e-1">-4.722579799912635e-1 -1.513557456450369e-17 2.292850384222830e-1</k_point>
        <npw>8445</npw>
        <eigenvalues size="32">
          -1.241134853647563e0 -1.240917414199981e0 -6.237218564701497e-1 -6.191608277734648e-1 -5.563808646680437e-1
          -5.534280447915649e-1 -5.486848220628660e-1 -5.462608354589133e-1 -5.426453945709602e-1 -5.407776695690250e-1
          -5.025171466896110e-1 -4.991753666558982e-1 -4.940518477399209e-1 -4.920087129716444e-1 -1.100590703060188e-1
          -1.077909583212464e-1 -5.310331450935816e-2 -4.968447939795468e-2 -4.807021422676504e-2 -4.223341051373524e-2
          -3.593881968088342e-2 -1.946144586698916e-2 8.407700946860572e-2 9.050408188072881e-2 9.361393060973555e-2
          9.619724208860946e-2 1.034808687962814e-1 1.111299797637073e-1 1.208006991737176e-1 1.301248199593791e-1
          1.578417398651221e-1 1.602366739254510e-1
          </eigenvalues>
        <occupations size="32">
          1.000000000000000e0 1.000000000000000e0 1.000000000000000e0 1.000000000000000e0 1.000000000000000e0
          1.000000000000000e0 1.000000000000000e0 1.000000000000000e0 1.000000000000000e0 1.000000000000000e0
          1.000000000000000e0 1.000000000000000e0 1.000000000000000e0 1.000000000000000e0 1.000000000000000e0
          1.000000000000000e0 1.000000000000000e0 1.000000000000000e0 1.000000000000000e0 1.000000000000000e0
          1.000000000000000e0 1.000000000000000e0 1.000000000000000e0 1.000000000000000e0 1.000000000000000e0
          1.000000000000000e0 1.000000000000000e0 1.000000000000000e0 1.000000000000000e0 1.000000000000000e0
          1.000000000000000e0 1.000000000000000e0
          </occupations>
      </ks_energies>
      <ks_energies>
        <k_point weight="1.920000000000e-1">4.722579799912634e-1 5.453165437498972e-1 -7.642834614074729e-2</k_point>
        <npw>8450</npw>
        <eigenvalues size="32">
          -1.241038841031120e0 -1.241007264529707e0 -6.223083619272074e-1 -6.208414926023414e-1 -5.552532374177366e-1
          -5.532702471027360e-1 -5.506245185555247e-1 -5.466388243651553e-1 -5.418337229889692e-1 -5.406985665706086e-1
          -5.019349519618050e-1 -4.987804217802873e-1 -4.946490741877114e-1 -4.923052030993133e-1 -1.079135172792956e-1
          -1.058412232627117e-1 -5.491688908290167e-2 -5.019502826557735e-2 -4.576276572715612e-2 -4.215856823773962e-2
          -2.763066563222851e-2 -2.465809292529068e-2 8.067577787015672e-2 8.323960199755078e-2 9.216294166147227e-2
          9.483164925441184e-2 1.054671638673187e-1 1.082509133931088e-1 1.241354071459855e-1 1.255927642130077e-1
          1.600285463526152e-1 1.620852881999276e-1
          </eigenvalues>
        <occupations size="32">
          1.000000000000000e0 1.000000000000000e0 1.000000000000000e0 1.000000000000000e0 1.000000000000000e0
          1.000000000000000e0 1.000000000000000e0 1.000000000000000e0 1.000000000000000e0 1.000000000000000e0
          1.000000000000000e0 1.000000000000000e0 1.000000000000000e0 1.000000000000000e0 1.000000000000000e0
          1.000000000000000e0 1.000000000000000e0 1.000000000000000e0 1.000000000000000e0 1.000000000000000e0
          1.000000000000000e0 1.000000000000000e0 1.000000000000000e0 1.000000000000000e0 1.000000000000000e0
          1.000000000000000e0 1.000000000000000e0 1.000000000000000e0 1.000000000000000e0 1.000000000000000e0
          1.000000000000000e0 1.000000000000000e0
          </occupations>
      </ks_energies>
      <ks_energies>
        <k_point weight="9.600000000000e-2">2.361289899956317e-1 4.089874078124229e-1 1.028375792214503e-14</k_point>
        <npw>8447</npw>
        <eigenvalues size="32">
          -1.241160685994568e0 -1.240891907756820e0 -6.241470959620838e-1 -6.184941442825219e-1 -5.566153502175377e-1
          -5.538049416776609e-1 -5.498576117690104e-1 -5.446749529899449e-1 -5.434085644173172e-1 -5.399866246248650e-1
          -5.025908260746387e-1 -5.001322325796406e-1 -4.927593497602325e-1 -4.923492686919520e-1 -1.100960155456308e-1
          -1.072458840725643e-1 -5.531933219997770e-2 -4.756902444386500e-2 -4.603895109419943e-2 -4.334411785525235e-2
          -3.984745093008359e-2 -1.769214268988637e-2 8.377680630318311e-2 9.293023834874353e-2 9.398808890744927e-2
          9.418015413676242e-2 1.014879440745532e-1 1.108633425212012e-1 1.247512601461867e-1 1.296022134634585e-1
          1.579465209883267e-1 1.607235069472370e-1
          </eigenvalues>
        <occupations size="32">
          1.000000000000000e0 1.000000000000000e0 1.000000000000000e0 1.000000000000000e0 1.000000000000000e0
          1.000000000000000e0 1.000000000000000e0 1.000000000000000e0 1.000000000000000e0 1.000000000000000e0
          1.000000000000000e0 1.000000000000000e0 1.000000000000000e0 1.000000000000000e0 1.000000000000000e0
          1.000000000000000e0 1.000000000000000e0 1.000000000000000e0 1.000000000000000e0 1.000000000000000e0
          1.000000000000000e0 1.000000000000000e0 1.000000000000000e0 1.000000000000000e0 1.000000000000000e0
          1.000000000000000e0 1.000000000000000e0 1.000000000000000e0 1.000000000000000e0 1.000000000000000e0
          1.000000000000000e0 1.000000000000000e0
          </occupations>
      </ks_energies>
      <ks_energies>
        <k_point weight="9.600000000000e-2">-4.722579799912635e-1 2.726582718749486e-1 3.057133845630509e-1</k_point>
        <npw>8442</npw>
        <eigenvalues size="32">
          -1.241123311610305e0 -1.240926179557452e0 -6.253156492002436e-1 -6.173569462952340e-1 -5.585048526774239e-1
          -5.571537171374836e-1 -5.443292432539155e-1 -5.434677676779080e-1 -5.433187613946892e-1 -5.396317444989034e-1
          -5.057484223566141e-1 -5.019165208191373e-1 -4.916310206322686e-1 -4.905463755532310e-1 -1.130758738335313e-1
          -1.029931525864573e-1 -5.588072091765957e-2 -4.881237070917250e-2 -4.576485147865608e-2 -4.001558461677631e-2
          -3.377399314348855e-2 -2.262334802517798e-2 7.814893360437914e-2 8.874512330251857e-2 9.462482937530858e-2
          1.008517212553488e-1 1.026844135155185e-1 1.087532907640005e-1 1.192536933649529e-1 1.308894368561451e-1
          1.537287350385755e-1 1.642026495376963e-1
          </eigenvalues>
        <occupations size="32">
          1.000000000000000e0 1.000000000000000e0 1.000000000000000e0 1.000000000000000e0 1.000000000000000e0
          1.000000000000000e0 1.000000000000000e0 1.000000000000000e0 1.000000000000000e0 1.000000000000000e0
          1.000000000000000e0 1.000000000000000e0 1.000000000000000e0 1.000000000000000e0 1.000000000000000e0
          1.000000000000000e0 1.000000000000000e0 1.000000000000000e0 1.000000000000000e0 1.000000000000000e0
          1.000000000000000e0 1.000000000000000e0 1.000000000000000e0 1.000000000000000e0 1.000000000000000e0
          1.000000000000000e0 1.000000000000000e0 1.000000000000000e0 1.000000000000000e0 1.000000000000000e0
          1.000000000000000e0 1.000000000000000e0
          </occupations>
      </ks_energies>
      <ks_energies>
        <k_point weight="9.600000000000e-2">4.722579799912634e-1 8.179748156248458e-1 2.056751584429006e-14</k_point>
        <npw>8439</npw>
        <eigenvalues size="32">
          -1.241073920420841e0 -1.240971760160326e0 -6.239765836516398e-1 -6.191974491041230e-1 -5.570214214292944e-1
          -5.549873560727989e-1 -5.459494395045777e-1 -5.455651131054297e-1 -5.431337034425394e-1 -5.405328509314469e-1
          -5.048590277565492e-1 -4.996799688940047e-1 -4.933006600873528e-1 -4.909220477970449e-1 -1.101640624135470e-1
          -1.035253510934373e-1 -5.364923495501155e-2 -5.183761009547759e-2 -4.679663473267725e-2 -4.000618116236920e-2
          -2.832044936497449e-2 -2.368051697768078e-2 7.703335667587085e-2 8.437442896803535e-2 9.673552760528532e-2
          9.732124411885666e-2 1.027988572143772e-1 1.028093014595669e-1 1.233276407539638e-1 1.285144766214654e-1
          1.571009522319862e-1 1.644144780488927e-1
          </eigenvalues>
        <occupations size="32">
          1.000000000000000e0 1.000000000000000e0 1.000000000000000e0 1.000000000000000e0 1.000000000000000e0
          1.000000000000000e0 1.000000000000000e0 1.000000000000000e0 1.000000000000000e0 1.000000000000000e0
          1.000000000000000e0 1.000000000000000e0 1.000000000000000e0 1.000000000000000e0 1.000000000000000e0
          1.000000000000000e0 1.000000000000000e0 1.000000000000000e0 1.000000000000000e0 1.000000000000000e0
          1.000000000000000e0 1.000000000000000e0 1.000000000000000e0 1.000000000000000e0 1.000000000000000e0
          1.000000000000000e0 1.000000000000000e0 1.000000000000000e0 1.000000000000000e0 1.000000000000000e0
          1.000000000000000e0 1.000000000000000e0
          </occupations>
      </ks_energies>
      <ks_energies>
        <k_point weight="3.200000000000e-2">3.545553295645667e-18 -7.567787282251843e-18 2.292850384222830e-1</k_point>
        <npw>8406</npw>
        <eigenvalues size="32">
          -1.241237182294130e0 -1.240832853878536e0 -6.223633698444374e-1 -6.202761940229190e-1 -5.554609078151880e-1
          -5.554609078151749e-1 -5.460412567278967e-1 -5.460412567278940e-1 -5.424359290381714e-1 -5.401595499238809e-1
          -5.049743796490307e-1 -5.049743796489599e-1 -4.898289735559489e-1 -4.898289735558849e-1 -1.179436421819890e-1
          -1.106916826638061e-1 -5.137791004940490e-2 -5.132765549121602e-2 -5.132765549121514e-2 -4.510139061860369e-2
          -4.510139061860292e-2 -1.013981969996616e-2 9.227352676792094e-2 9.227352676794759e-2 9.840022786130989e-2
          9.840022786131861e-2 1.115512373719206e-1 1.115512373719321e-1 1.355852422961268e-1 1.355852422961652e-1
          1.456580079060198e-1 1.586681730742169e-1
          </eigenvalues>
        <occupations size="32">
          1.000000000000000e0 1.000000000000000e0 1.000000000000000e0 1.000000000000000e0 1.000000000000000e0
          1.000000000000000e0 1.000000000000000e0 1.000000000000000e0 1.000000000000000e0 1.000000000000000e0
          1.000000000000000e0 1.000000000000000e0 1.000000000000000e0 1.000000000000000e0 1.000000000000000e0
          1.000000000000000e0 1.000000000000000e0 1.000000000000000e0 1.000000000000000e0 1.000000000000000e0
          1.000000000000000e0 1.000000000000000e0 1.000000000000000e0 1.000000000000000e0 1.000000000000000e0
          1.000000000000000e0 1.000000000000000e0 1.000000000000000e0 1.000000000000000e0 1.000000000000000e0
          1.000000000000000e0 1.000000000000000e0
          </occupations>
      </ks_energies>
      <ks_energies>
        <k_point weight="9.600000000000e-2">-2.361289899956318e-1 -1.363291359374743e-1 3.057133845630406e-1</k_point>
        <npw>8432</npw>
        <eigenvalues size="32">
          -1.241165763968738e0 -1.240896363032238e0 -6.225221668287702e-1 -6.203303673984497e-1 -5.561084596745679e-1
          -5.518483572085008e-1 -5.509831141798150e-1 -5.437385622222600e-1 -5.434035563566795e-1 -5.412410436400008e-1
          -5.040247434699403e-1 -4.983382204531119e-1 -4.954461745637332e-1 -4.902777531752037e-1 -1.142924558926637e-1
          -1.106179363796248e-1 -5.101276495463796e-2 -5.048745092682187e-2 -4.639262526828829e-2 -4.626782215559308e-2
          -4.050559807097612e-2 -1.659340166044605e-2 9.145849593283730e-2 9.427125218558189e-2 9.638620951858893e-2
          9.904021037144133e-2 1.027035750074639e-1 1.134053005631386e-1 1.258765089724334e-1 1.307454219436539e-1
          1.527626922470509e-1 1.579326221996951e-1
          </eigenvalues>
        <occupations size="32">
          1.000000000000000e0 1.000000000000000e0 1.000000000000000e0 1.000000000000000e0 1.000000000000000e0
          1.000000000000000e0 1.000000000000000e0 1.000000000000000e0 1.000000000000000e0 1.000000000000000e0
          1.000000000000000e0 1.000000000000000e0 1.000000000000000e0 1.000000000000000e0 1.000000000000000e0
          1.000000000000000e0 1.000000000000000e0 1.000000000000000e0 1.000000000000000e0 1.000000000000000e0
          1.000000000000000e0 1.000000000000000e0 1.000000000000000e0 1.000000000000000e0 1.000000000000000e0
          1.000000000000000e0 1.000000000000000e0 1.000000000000000e0 1.000000000000000e0 1.000000000000000e0
          1.000000000000000e0 1.000000000000000e0
          </occupations>
      </ks_energies>
      <ks_energies>
        <k_point weight="9.600000000000e-2">7.083869699868952e-1 4.089874078124229e-1 1.029795286650736e-14</k_point>
        <npw>8410</npw>
        <eigenvalues size="32">
          -1.241040972809031e0 -1.241008754964428e0 -6.225340422224862e-1 -6.205598931368097e-1 -5.565075486834090e-1
          -5.524831259608045e-1 -5.501102194658273e-1 -5.467841176535506e-1 -5.417729218388299e-1 -5.402896885137246e-1
          -5.012045116718841e-1 -4.996693156333237e-1 -4.951635597632135e-1 -4.918604234481755e-1 -1.109087770460187e-1
          -1.055533981893704e-1 -5.478553679668968e-2 -4.895567423023453e-2 -4.602548452650648e-2 -4.329091589764255e-2
          -2.879317275418021e-2 -2.501869006072410e-2 8.226548431967744e-2 8.728226116735225e-2 9.297215860982423e-2
          9.725732892979210e-2 1.051623828849371e-1 1.168715698333094e-1 1.169362359730954e-1 1.245987957228709e-1
          1.570288978323907e-1 1.614121018178549e-1
          </eigenvalues>
        <occupations size="32">
          1.000000000000000e0 1.000000000000000e0 1.000000000000000e0 1.000000000000000e0 1.000000000000000e0
          1.000000000000000e0 1.000000000000000e0 1.000000000000000e0 1.000000000000000e0 1.000000000000000e0
          1.000000000000000e0 1.000000000000000e0 1.000000000000000e0 1.000000000000000e0 1.000000000000000e0
          1.000000000000000e0 1.000000000000000e0 1.000000000000000e0 1.000000000000000e0 1.000000000000000e0
          1.000000000000000e0 1.000000000000000e0 1.000000000000000e0 1.000000000000000e0 1.000000000000000e0
          1.000000000000000e0 1.000000000000000e0 1.000000000000000e0 1.000000000000000e0 1.000000000000000e0
          1.000000000000000e0 1.000000000000000e0
          </occupations>
      </ks_energies>
      <ks_energies>
        <k_point weight="9.600000000000e-2">4.722579799912635e-1 2.726582718749486e-1 7.642834614076788e-2</k_point>
        <npw>8455</npw>
        <eigenvalues size="32">
          -1.241133530024003e0 -1.240916489150209e0 -6.246744496163210e-1 -6.179491716966298e-1 -5.568674540616881e-1
          -5.559740520547933e-1 -5.479065542015027e-1 -5.454038259001215e-1 -5.427348138976097e-1 -5.390239735675331e-1
          -5.041988867049899e-1 -4.987792139307270e-1 -4.939592227730628e-1 -4.914710756459048e-1 -1.113031436341214e-1
          -1.045151110085946e-1 -5.637434318135815e-2 -4.785044507894821e-2 -4.367839105672418e-2 -4.361790142312270e-2
          -3.638042813899316e-2 -2.047384266715398e-2 7.982636706673052e-2 8.946901662354552e-2 9.223667420649797e-2
          9.862010832606860e-2 1.022214448347155e-1 1.162128451970668e-1 1.181589745709474e-1 1.290555550207265e-1
          1.559294658645794e-1 1.628523841330419e-1
          </eigenvalues>
        <occupations size="32">
          1.000000000000000e0 1.000000000000000e0 1.000000000000000e0 1.000000000000000e0 1.000000000000000e0
          1.000000000000000e0 1.000000000000000e0 1.000000000000000e0 1.000000000000000e0 1.000000000000000e0
          1.000000000000000e0 1.000000000000000e0 1.000000000000000e0 1.000000000000000e0 1.000000000000000e0
          1.000000000000000e0 1.000000000000000e0 1.000000000000000e0 1.000000000000000e0 1.000000000000000e0
          1.000000000000000e0 1.000000000000000e0 1.000000000000000e0 1.000000000000000e0 1.000000000000000e0
          1.000000000000000e0 1.000000000000000e0 1.000000000000000e0 1.000000000000000e0 1.000000000000000e0
          1.000000000000000e0 1.000000000000000e0
          </occupations>
      </ks_energies>
      <ks_energies>
        <k_point weight="9.600000000000e-2">-2.361289899956318e-1 1.363291359374743e-1 3.821417307038085e-1</k_point>
        <npw>8423</npw>
        <eigenvalues size="32">
          -1.241139735118013e0 -1.240922062933944e0 -6.230967030463635e-1 -6.198419037197615e-1 -5.560458252008748e-1
          -5.515144466465260e-1 -5.493801411894427e-1 -5.457817567572716e-1 -5.429211138833367e-1 -5.422361623592742e-1
          -5.016838577374713e-1 -4.986643471620765e-1 -4.945328196104551e-1 -4.925526418450151e-1 -1.128688964255632e-1
          -1.127789554150093e-1 -5.158294307463736e-2 -4.855179428910156e-2 -4.812498364676316e-2 -4.380531648761290e-2
          -3.833234885510553e-2 -1.969324270670283e-2 9.086749441522224e-2 9.283580677270169e-2 9.634004443469861e-2
          9.834127365755073e-2 1.078748709342783e-1 1.154445797352671e-1 1.195574977813419e-1 1.320257398840276e-1
          1.539355552779454e-1 1.557617447250222e-1
          </eigenvalues>
        <occupations size="32">
          1.000000000000000e0 1.000000000000000e0 1.000000000000000e0 1.000000000000000e0 1.000000000000000e0
          1.000000000000000e0 1.000000000000000e0 1.000000000000000e0 1.000000000000000e0 1.000000000000000e0
          1.000000000000000e0 1.000000000000000e0 1.000000000000000e0 1.000000000000000e0 1.000000000000000e0
          1.000000000000000e0 1.000000000000000e0 1.000000000000000e0 1.000000000000000e0 1.000000000000000e0
          1.000000000000000e0 1.000000000000000e0 1.000000000000000e0 1.000000000000000e0 1.000000000000000e0
          1.000000000000000e0 1.000000000000000e0 1.000000000000000e0 1.000000000000000e0 1.000000000000000e0
          1.000000000000000e0 1.000000000000000e0
          </occupations>
      </ks_energies>
      <ks_energies>
        <k_point weight="1.920000000000e-1">7.083869699868952e-1 6.816456796873714e-1 7.642834614077819e-2</k_point>
        <npw>8424</npw>
        <eigenvalues size="32">
          -1.241067393596071e0 -1.240984337825835e0 -6.225019774404120e-1 -6.207672581001649e-1 -5.553400769729199e-1
          -5.537804035821234e-1 -5.468272299821505e-1 -5.462742464174363e-1 -5.433153563749046e-1 -5.423858040704090e-1
          -5.012830406777679e-1 -4.992672982727245e-1 -4.942626120500691e-1 -4.927956087405306e-1 -1.097518028706472e-1
          -1.089084624082839e-1 -5.151621543527815e-2 -5.129659676157347e-2 -4.687258711136158e-2 -4.274334064579746e-2
          -2.989134065822687e-2 -2.404722651033348e-2 8.470391721777323e-2 8.664258040314630e-2 9.683268064631608e-2
          9.924671234889487e-2 1.037984836296978e-1 1.080262506638097e-1 1.209571072966309e-1 1.269549088153712e-1
          1.580713922939496e-1 1.590871181428865e-1
          </eigenvalues>
        <occupations size="32">
          1.000000000000000e0 1.000000000000000e0 1.000000000000000e0 1.000000000000000e0 1.000000000000000e0
          1.000000000000000e0 1.000000000000000e0 1.000000000000000e0 1.000000000000000e0 1.000000000000000e0
          1.000000000000000e0 1.000000000000000e0 1.000000000000000e0 1.000000000000000e0 1.000000000000000e0
          1.000000000000000e0 1.000000000000000e0 1.000000000000000e0 1.000000000000000e0 1.000000000000000e0
          1.000000000000000e0 1.000000000000000e0 1.000000000000000e0 1.000000000000000e0 1.000000000000000e0
          1.000000000000000e0 1.000000000000000e0 1.000000000000000e0 1.000000000000000e0 1.000000000000000e0
          1.000000000000000e0 1.000000000000000e0
          </occupations>
      </ks_energies>
      <ks_energies>
        <k_point weight="1.920000000000e-1">4.722579799912635e-1 5.453165437498972e-1 1.528566922815358e-1</k_point>
        <npw>8443</npw>
        <eigenvalues size="32">
          -1.241064247900797e0 -1.240981594342641e0 -6.235110591324871e-1 -6.196547033196362e-1 -5.563976060137502e-1
          -5.543294765495928e-1 -5.491393530104070e-1 -5.437065917480520e-1 -5.432226665238398e-1 -5.408232393113424e-1
          -5.041965193588821e-1 -4.984747912870570e-1 -4.946345515126461e-1 -4.910400132169012e-1 -1.095515255423698e-1
          -1.041595623582790e-1 -5.542713196482247e-2 -5.000749585402728e-2 -4.381156690390672e-2 -4.332533285867955e-2
          -2.870711233153248e-2 -2.341505466601231e-2 7.808430460865468e-2 8.428015347186825e-2 9.326076447350797e-2
          9.733015124861325e-2 1.032463338782173e-1 1.066216387884981e-1 1.238060094953155e-1 1.267712368653722e-1
          1.580395600764575e-1 1.637546957398664e-1
          </eigenvalues>
        <occupations size="32">
          1.000000000000000e0 1.000000000000000e0 1.000000000000000e0 1.000000000000000e0 1.000000000000000e0
          1.000000000000000e0 1.000000000000000e0 1.000000000000000e0 1.000000000000000e0 1.000000000000000e0
          1.000000000000000e0 1.000000000000000e0 1.000000000000000e0 1.000000000000000e0 1.000000000000000e0
          1.000000000000000e0 1.000000000000000e0 1.000000000000000e0 1.000000000000000e0 1.000000000000000e0
          1.000000000000000e0 1.000000000000000e0 1.000000000000000e0 1.000000000000000e0 1.000000000000000e0
          1.000000000000000e0 1.000000000000000e0 1.000000000000000e0 1.000000000000000e0 1.000000000000000e0
          1.000000000000000e0 1.000000000000000e0
          </occupations>
      </ks_energies>
      <ks_energies>
        <k_point weight="9.600000000000e-2">7.083869699868952e-1 -4.089874078124229e-1 -2.292850384222932e-1</k_point>
        <npw>8423</npw>
        <eigenvalues size="32">
          -1.241075616162166e0 -1.240973698974329e0 -6.245427368885556e-1 -6.184236274550389e-1 -5.586738339141436e-1
          -5.553935782364119e-1 -5.455622349383598e-1 -5.439391400246603e-1 -5.430443023056986e-1 -5.398214229437843e-1
          -5.037986816698488e-1 -5.029574144100469e-1 -4.918753816428905e-1 -4.908869444154069e-1 -1.129870081391727e-1
          -1.034843038226315e-1 -5.608637967654405e-2 -4.823896392767959e-2 -4.423986169918003e-2 -4.225944331965634e-2
          -2.985751776742742e-2 -2.525201976428942e-2 7.902055207883794e-2 8.754726652877000e-2 9.724125819785700e-2
          1.006296535569471e-1 1.017499692675768e-1 1.081960423245429e-1 1.202025733782908e-1 1.277403769617440e-1
          1.542625419349300e-1 1.635278376600575e-1
          </eigenvalues>
        <occupations size="32">
          1.000000000000000e0 1.000000000000000e0 1.000000000000000e0 1.000000000000000e0 1.000000000000000e0
          1.000000000000000e0 1.000000000000000e0 1.000000000000000e0 1.000000000000000e0 1.000000000000000e0
          1.000000000000000e0 1.000000000000000e0 1.000000000000000e0 1.000000000000000e0 1.000000000000000e0
          1.000000000000000e0 1.000000000000000e0 1.000000000000000e0 1.000000000000000e0 1.000000000000000e0
          1.000000000000000e0 1.000000000000000e0 1.000000000000000e0 1.000000000000000e0 1.000000000000000e0
          1.000000000000000e0 1.000000000000000e0 1.000000000000000e0 1.000000000000000e0 1.000000000000000e0
          1.000000000000000e0 1.000000000000000e0
          </occupations>
      </ks_energies>
      <ks_energies>
        <k_point weight="3.200000000000e-2">7.091106591291334e-18 -1.513557456450369e-17 4.585700768445661e-1</k_point>
        <npw>8394</npw>
        <eigenvalues size="32">
          -1.241111829593768e0 -1.240957402381871e0 -6.218260041266835e-1 -6.210277573689254e-1 -5.530899604596417e-1
          -5.530899604596311e-1 -5.495924406747394e-1 -5.495924406747317e-1 -5.415843489021416e-1 -5.407177386368742e-1
          -4.996626979924820e-1 -4.996626979924143e-1 -4.939781319711100e-1 -4.939781319710448e-1 -1.171562045804200e-1
          -1.145958613754622e-1 -4.925152444690065e-2 -4.925152444689915e-2 -4.688174412046786e-2 -4.688174412046613e-2
          -3.706840953539154e-2 -2.144630659693898e-2 9.418752122450078e-2 9.418752122452151e-2 9.655060213083560e-2
          9.655060213084514e-2 1.181821208156945e-1 1.181821208157052e-1 1.273482789686133e-1 1.273482789686405e-1
          1.489961846606576e-1 1.538257097799249e-1
          </eigenvalues>
        <occupations size="32">
          1.000000000000000e0 1.000000000000000e0 1.000000000000000e0 1.000000000000000e0 1.000000000000000e0
          1.000000000000000e0 1.000000000000000e0 1.000000000000000e0 1.000000000000000e0 1.000000000000000e0
          1.000000000000000e0 1.000000000000000e0 1.000000000000000e0 1.000000000000000e0 1.000000000000000e0
          1.000000000000000e0 1.000000000000000e0 1.000000000000000e0 1.000000000000000e0 1.000000000000000e0
          1.000000000000000e0 1.000000000000000e0 1.000000000000000e0 1.000000000000000e0 1.000000000000000e0
          1.000000000000000e0 1.000000000000000e0 1.000000000000000e0 1.000000000000000e0 1.000000000000000e0
          1.000000000000000e0 1.000000000000000e0
          </occupations>
      </ks_energies>
      <ks_energies>
        <k_point weight="9.600000000000e-2">9.445159599825271e-1 5.453165437498972e-1 1.528566922815358e-1</k_point>
        <npw>8393</npw>
        <eigenvalues size="32">
          -1.241046742598965e0 -1.241014774724245e0 -6.218632213925064e-1 -6.212067857093645e-1 -5.558436427315008e-1
          -5.522944901185488e-1 -5.496421782171684e-1 -5.458784826173199e-1 -5.426089987980424e-1 -5.413048118435771e-1
          -5.012669376998511e-1 -4.973628047574626e-1 -4.964755448146827e-1 -4.924872477350963e-1 -1.143857143710741e-1
          -1.121313321921415e-1 -5.091260314862243e-2 -4.736870263847170e-2 -4.724847795286800e-2 -4.625884233220839e-2
          -3.026019605557503e-2 -2.664287568384572e-2 9.078659961689759e-2 9.282195265267534e-2 9.700521643710614e-2
          9.775229442080564e-2 1.092919623025443e-1 1.166726300608901e-1 1.221467613099197e-1 1.252780216048115e-1
          1.535174068670318e-1 1.556537809137083e-1
          </eigenvalues>
        <occupations size="32">
          1.000000000000000e0 1.000000000000000e0 1.000000000000000e0 1.000000000000000e0 1.000000000000000e0
          1.000000000000000e0 1.000000000000000e0 1.000000000000000e0 1.000000000000000e0 1.000000000000000e0
          1.000000000000000e0 1.000000000000000e0 1.000000000000000e0 1.000000000000000e0 1.000000000000000e0
          1.000000000000000e0 1.000000000000000e0 1.000000000000000e0 1.000000000000000e0 1.000000000000000e0
          1.000000000000000e0 1.000000000000000e0 1.000000000000000e0 1.000000000000000e0 1.000000000000000e0
          1.000000000000000e0 1.000000000000000e0 1.000000000000000e0 1.000000000000000e0 1.000000000000000e0
          1.000000000000000e0 1.000000000000000e0
          </occupations>
      </ks_energies>
    </band_structure>
    <forces rank="2" dims="3 10" order="F">
      0.000000000000000e0 0.000000000000000e0 0.000000000000000e0
      -1.925657672750930e-45 -3.335406458547581e-29 1.869883481480501e-29
      -5.777093450096858e-29 3.335406458547581e-29 -1.869883481480500e-29
      5.777093450096858e-29 1.000621937564274e-28 2.508594560671241e-42
      -1.920780747654734e-4 3.326889845138667e-4 8.360752655749700e-18
      3.841561495309469e-4 1.362701936979378e-20 7.227298559769075e-21
      -1.920780747654734e-4 -3.326889845138667e-4 -8.352389471907745e-18
      -3.841561495309469e-4 -1.362701936979378e-20 -7.227298559769075e-21
      1.920780747654734e-4 3.326889845138667e-4 8.352389471907745e-18
      1.920780747654735e-4 -3.326889845138667e-4 -8.333558407126256e-18
      </forces>
    <stress rank="2" dims="3 3" order="F">
      -1.049610544924273e-4 -7.923660133782027e-21 -1.138598399985545e-20
      -3.584786993743075e-20 -1.049610544924610e-4 -2.623632938295156e-18
      -4.746895522946410e-21 -2.618758382394747e-18 6.847339103986659e-5
      </stress>
  </output>
  <status>0</status>
  <timing_info>
    <total label="PWSCF">
      <cpu>2.535957730000000e2</cpu>
      <wall>2.841790030002594e2</wall>
    </total>
    <partial label="electrons" calls="4">
      <cpu>2.474547850000000e2</cpu>
      <wall>2.755724706649781e2</wall>
    </partial>
  </timing_info>
  <closed DATE=" 4 May 2022" TIME="14: 2:33"></closed>
</qes:espresso>
